cosmos_ai_orchestrator/__init__.py
cosmos_ai_orchestrator/orchestrator.py
cosmos_ai_orchestrator-0.1.2.dist-info/METADATA
cosmos_ai_orchestrator-0.1.2.dist-info/WHEEL
cosmos_ai_orchestrator-0.1.2.dist-info/top_level.txt
cosmos_ai_orchestrator-0.1.2.dist-info/RECORD
