Metadata-Version: 2.4
Name: cosmos_ai_orchestrator
Version: 0.1.2
Summary: A reusable toolkit integrating Azure OpenAI and Cosmos DB for semantic search and embeddings orchestration.
Home-page: https://github.com/vamsichowdaryg/cosmos_ai_orchestrator
Author: Vamsi Gudapati
Author-email: vamsi7673916775@gmail.com
License: MIT
Project-URL: Bug Tracker, https://github.com/vamsichowdaryg/cosmos_ai_orchestrator/issues
Project-URL: Source Code, https://github.com/vamsichowdaryg/cosmos_ai_orchestrator
Keywords: Azure OpenAI,Cosmos DB,Semantic Search,Embeddings,AI Orchestration,Azure,Toolkit
Classifier: Programming Language :: Python :: 3
Classifier: Framework :: FastAPI
Classifier: License :: OSI Approved :: MIT License
Classifier: Operating System :: OS Independent
Classifier: Topic :: Software Development :: Libraries :: Python Modules
Classifier: Intended Audience :: Developers
Classifier: Development Status :: 4 - Beta
Requires-Python: >=3.8
Requires-Dist: openai>=1.3.0
Requires-Dist: azure-cosmos>=4.5.0
Requires-Dist: typing-extensions>=4.0.0
Dynamic: author
Dynamic: author-email
Dynamic: classifier
Dynamic: description-content-type
Dynamic: home-page
Dynamic: keywords
Dynamic: license
Dynamic: project-url
Dynamic: requires-dist
Dynamic: requires-python
Dynamic: summary
